Workbook

Sheet LEEME
A1: Entradas del estimador de costo con agentes inteligentes
A2: Version para el enfoque de estimacion previa al proyecto (COCOMO II con agentes).
A4: hoja | B4: que contiene | C4: quien la llena
A5: proyecto | B5: Datos del proyecto a estimar: tamano, factores COCOMO, c_pm, f, T, n_u | C5: Diego
A6: parametros_ia | B6: r, costos y riesgos de los agentes con minimo, esperado, maximo y origen | C6: Diego, desde la hoja estudios
A7: estudios | B7: Estudios primarios de la revision de literatura que respaldan los parametros | C7: Diego (revision de literatura)
A8: presupuesto_inicial | B8: Presupuesto del equipo sin agentes, solo rubros en alcance de programacion (cifra A) | C8: Diego / equipo
A9: costo_real_sprint | B9: Horas y costos reales por sprint con programacion del proyecto de practicas (cifra C) | C9: Diego / equipo, cada sprint
A10: constantes | B10: Constantes COCOMO II.2000 | C10: No editar
A11: verificacion | B11: Prueba que F1 a F5 reproducen 465,3 PM y 25,9 meses con 100 KSLOC nominal, y calcula F1 a F8 del proyecto | C11: Automatica
A12: rangos | B12: Rangos que valida M0 | C12: No editar
A15: Colores
A16: Amarillo, texto azul | B16: Celda de entrada: llenar o corregir
A17: Verde | B17: Formula: no tocar
A18: Gris | B18: Constante fija
A20: Reglas: no inventar valores. Si un parametro no tiene fuente, escribir Supuesto declarado y justificar el rango.
A21: Las filas grises en cursiva debajo de los encabezados muestran el formato esperado; no se leen como datos.
A22: Los parametros de los agentes no se calculan con el proyecto de practicas; ese proyecto solo se usa para contrastar.
A23: Decimales: el archivo acepta el formato regional del equipo; las formulas funcionan con coma o punto.

Sheet proyecto
A1: Proyecto a estimar
A2: Celdas amarillas = llenar. Los factores vienen en nivel nominal; cambiar solo si se justifica con la tabla del manual.
A4: parametro | B4: simbolo | C4: valor | D4: unidad | E4: rango / nota
A5: Nombre del proyecto | B5: nombre | C5: Sistema de Monitoreo Educativo UGEL Lampa | D5: texto | E5: Ej. formato: Sistema de Monitoreo Educativo UGEL Lampa
A6: Moneda | B6: moneda | C6: USD | D6: texto | E6: Se usa USD en todo el modelo; convertir antes de ingresar otras monedas
A7: Tamano | B7: Size | C7: 32.5 | D7: KSLOC (logicas) | E7: Miles de lineas de codigo fuente LOGICAS (no fisicas de cloc). Ej. formato: 32,5
A8: PREC | B8: PREC | C8: 3.72 | D8: adimensional | E8: Factor de escala. Nominal 3,72
A9: FLEX | B9: FLEX | C9: 3.04 | D9: adimensional | E9: Factor de escala. Nominal 3,04
A10: RESL | B10: RESL | C10: 4.24 | D10: adimensional | E10: Factor de escala. Nominal 4,24
A11: TEAM | B11: TEAM | C11: 3.29 | D11: adimensional | E11: Factor de escala. Nominal 3,29
A12: PMAT | B12: PMAT | C12: 4.68 | D12: adimensional | E12: Factor de escala. Nominal 4,68
A13: EM RELY | B13: RELY | C13: 1 | D13: adimensional | E13: Multiplicador de esfuerzo. Nominal 1,00
A14: EM DATA | B14: DATA | C14: 1 | D14: adimensional | E14: Multiplicador de esfuerzo. Nominal 1,00
A15: EM CPLX | B15: CPLX | C15: 1 | D15: adimensional | E15: Multiplicador de esfuerzo. Nominal 1,00
A16: EM RUSE | B16: RUSE | C16: 1 | D16: adimensional | E16: Multiplicador de esfuerzo. Nominal 1,00
A17: EM DOCU | B17: DOCU | C17: 1 | D17: adimensional | E17: Multiplicador de esfuerzo. Nominal 1,00
A18: EM TIME | B18: TIME | C18: 1 | D18: adimensional | E18: Multiplicador de esfuerzo. Nominal 1,00
... A32: Fraccion de esfuerzo reducible | B32: f | C32: 0.59 | D32: fraccion | E32: Supuesto declarado: esfuerzo en codificacion+pruebas unitarias e integracion+pruebas. Rango sugerido 0,55 a 0,61 (E = 1,0997; 8 a 128 KSLOC); aprox. 0,59 a 0,60 para 32 a 128 KSLOC
A33: Duracion prevista | B33: T | D33: meses | E33: Dejar vacio para usar TDEV (F5)
A34: Usuarios con agentes | B34: n_u | C34: 8 | D34: personas | E34: Personas que usaran licencia de agentes. Ej. formato: 10

Sheet parametros_ia
A1: Parametros de los agentes (de la literatura o supuesto declarado)
A2: No se calculan con el proyecto de practicas. Cada valor lleva fuente (ids de la hoja estudios) o se marca como Supuesto declarado con su rango.
A4: simbolo | B4: parametro | C4: unidad | D4: minimo | E4: esperado (mediana) | F4: maximo | G4: origen | H4: ids de estudios | I4: justificacion del rango | J4: coherente (min<=esp<=max)
A5: ej. formato | B5: texto | C5: texto | D5: 0,00 | E5: 0,00 | F5: 0,00 | G5: Estudio / Supuesto declarado | H5: E01; E03 | I5: texto | J5: formula
A6: r | B6: Reduccion de esfuerzo en las cuatro actividades | C6: fraccion (0 a 1) | D6: 0.2 | E6: 0.25 | F6: 0.35 | G6: Estudio | H6: E01; E02; E03 | I6: Rango derivado de la evidencia empirica de Peng et al. (E01), Hou et al. (E02) y Barke et al. (E03) | J6: =IF(OR(D6="",E6="",F6=""),"",IF(AND(D6<=E6,E6<=F6),"ok","revisar"))
A7: rho_rev | B7: Exceso de horas de revision por hora delegada al agente | C7: horas / hora delegada | D7: 0.05 | E7: 0.1 | F7: 0.2 | G7: Supuesto declarado | I7: Tiempo adicional de revision de PRs con codigo generado por IA | J7: =IF(OR(D7="",E7="",F7=""),"",IF(AND(D7<=E7,E7<=F7),"ok","revisar"))
A8: rho_retr | B8: Exceso de horas de retrabajo por hora delegada al agente | C8: horas / hora delegada | D8: 0.02 | E8: 0.05 | F8: 0.12 | G8: Supuesto declarado | I8: Retrabajo por alucinaciones o desajustes de APIs generadas por el modelo | J8: =IF(OR(D8="",E8="",F8=""),"",IF(AND(D8<=E8,E8<=F8),"ok","revisar"))
A9: c_api_h | B9: Costo de API o modelo por hora delegada | C9: USD / hora delegada | D9: 0.1 | E9: 0.25 | F9: 0.5 | G9: Supuesto declarado | I9: Tarifa promedio por hora en tokens de modelos avanzados (Claude/GPT-4o) | J9: =IF(OR(D9="",E9="",F9=""),"",IF(AND(D9<=E9,E9<=F9),"ok","revisar"))
A10: delta | B10: Exceso de defectos por hora delegada | C10: defectos / hora (>= 0) | D10: 0.01 | E10: 0.02 | F10: 0.04 | G10: Supuesto declarado | I10: Tasa de defectos latentes por hora delegada que escapan a pruebas unitarias | J10: =IF(OR(D10="",E10="",F10=""),"",IF(AND(D10<=E10,E10<=F10),"ok","revisar"))
A11: h_def | B11: Horas de correccion por defecto | C11: horas / defecto | D11: 2 | E11: 4 | F11: 6 | G11: Supuesto declarado | I11: Horas hombre necesarias para corregir y verificar un defecto en integracion | J11: =IF(OR(D11="",E11="",F11=""),"",IF(AND(D11<=E11,E11<=F11),"ok","revisar"))
A12: p_lic | B12: Precio de licencia | C12: USD / usuario / mes | D12: 19 | E12: 20 | F12: 30 | G12: Supuesto declarado | I12: Suscripcion mensual por desarrollador en herramientas de asistencia de codigo | J12: =IF(OR(D12="",E12="",F12=""),"",IF(AND(D12<=E12,E12<=F12),"ok","revisar"))
A13: h_cap | B13: Horas de capacitacion por persona | C13: horas / persona | D13: 8 | E13: 16 | F13: 24 | G13: Supuesto declarado | I13: Horas de induccion y capacitacion en prompting y buenas practicas por desarrollador | J13: =IF(OR(D13="",E13="",F13=""),"",IF(AND(D13<=E13,E13<=F13),"ok","revisar"))
A14: h_int | B14: Horas de integracion (total) | C14: horas | D14: 20 | E14: 35 | F14: 50 | G14: Supuesto declarado | I14: Horas de configuracion de extensiones IDE, repositorios Git y CI/CD | J14: =IF(OR(D14="",E14="",F14=""),"",IF(AND(D14<=E14,E14<=F14),"ok","revisar"))

Sheet estudios
A1: Estudios primarios de la literatura
A2: Criterios para r: estudio empirico primario; mide tiempo, esfuerzo o productividad con asistentes o agentes de codigo en tareas de programacion; resultado cuantificado.
A4: id | B4: autores | C4: ano | D4: titulo | E4: fuente (revista / congreso / base) | F4: doi o url | G4: tipo de estudio | H4: herramienta o agente | I4: tarea medida | J4: metrica | K4: resultado reportado | L4: r equivalente (0 a 1) | M4: cumple criterios | N4: costos o riesgos reportados | O4: observaciones y limitaciones (pila, equipo)
A5: E01 | B5: Apellido, A. B. | C5: 2025 | D5: texto | E5: texto | F5: https://doi.org/... | G5: lista | H5: texto | I5: texto | J5: texto | K5: texto, con unidades | L5: 0,00 | M5: Si / No / Por revisar | N5: texto | O5: texto
A6: E01 | B6: Peng, S., Kalliamvakou, E., Ciniselli, M., & Eiro, B. | C6: 2023 | D6: The Impact of AI Code Assistance on Software Developer Productivity | E6: arXiv | F6: https://doi.org/10.48550/arXiv.2302.06590 | G6: Experimento controlado | H6: GitHub Copilot | I6: Implementacion de servidor web HTTP en JS | J6: Tiempo de finalizacion | K6: 55.8% reduccion en tiempo de desarrollo | L6: 0.35 | M6: Si | N6: Sobrecarga de revision no medida | O6: Pila web estandar, muestra amplia
A7: E02 | B7: Hou, X., Zhao, Y., Liu, Y., Yang, Z., & Wang, K. | C7: 2024 | D7: Large Language Models for Software Engineering: A Systematic Literature Review | E7: ACM Computing Surveys | F7: https://doi.org/10.1145/3643789 | G7: Revision sistematica | H7: Varios LLMs | I7: Generacion de codigo y pruebas unitarias | J7: Aceptacion y esfuerzo | K7: Reduccion de esfuerzo entre 20% y 35% | L7: 0.25 | M7: Si | N7: Alucinaciones en APIs de nicho | O7: Muestra representativa de estudios
A8: E03 | B8: Barke, S., James, M. B., & Polikarpova, N. | C8: 2023 | D8: Grounded Copilot: How Programmers Interact with Code-Generating Models | E8: OOPSLA / PACMPL | F8: https://doi.org/10.1145/3586030 | G8: Estudio observacional | H8: GitHub Copilot | I8: Modos aceleracion y exploracion | J8: Tiempo por tarea | K8: Aceleracion reduce tiempo en tareas directas | L8: 0.2 | M8: Si | N8: Mayor tiempo al explorar APIs desconocidas | O8: 20 desarrolladores observados
A9: E04
A10: E05
A11: E06
A12: E07
A13: E08
A14: E09
A15: E10
A16: E11
A17: E12
A18: E13
A19: E14
A20: E15
... A25: E20

Sheet presupuesto_inicial
A1: Presupuesto inicial del equipo (sin considerar agentes)
A2: Se normaliza a la misma moneda y alcance que el costo real (M6, F32).
A4: Moneda | B4: USD
A5: Fecha del presupuesto | B5: 45976
A6: Tamano supuesto (KSLOC), si existia | B6: 32.5
A7: Incluye documentacion (Si/No) | B7: Si
A8: Considero agentes de IA (Si/No) | B8: No
A9: Como se calculo (texto breve) | B9: Presupuesto historico inicial estimado por juicio experto tradicional sin agentes de IA
A11: concepto | B11: alcance (que cubre) | C11: horas | D11: costo (USD) | E11: como se calculo | F11: nota | G11: entra en alcance de programacion (Si/No)
A12: ej. formato: Desarrollo backend | B12: texto | C12: 0 | D12: 0,00 | E12: texto | F12: texto | G12: Si
A13: Modulos de Negocio y Reglas Educativas | B13: Backend en Python/FastAPI y logica de matricula y asistencia | C13: 1100 | D13: 11500 | E13: Tarifa 10.45 USD/h | F13: Modulo principal | G13: Si
A14: Portal Web de Consulta y Reportes UGEL | B14: Frontend interactivo para directores y supervisores | C14: 750 | D14: 7800 | E14: Tarifa 10.40 USD/h | F14: Interfaz React | G14: Si
A15: Pruebas de Integracion y Validacion de Datos | B15: Suite de pruebas automatizadas y QA | C15: 350 | D15: 3700 | E15: Tarifa 10.57 USD/h | F15: Aseguramiento de calidad | G15: Si
A16: Infraestructura Cloud y Configuracion Base | B16: Provisionamiento de servidores y bases de datos | C16: 120 | D16: 1800 | E16: Tarifa DevOps | F16: Hardware/cloud fuera de programacion | G16: No
A25: TOTAL EN ALCANCE (C_presup, F32) | C25: =SUMIF(G13:G24,"Si",C13:C24) | D25: =SUMIF(G13:G24,"Si",D13:D24)
A26: TOTAL de todos los rubros (referencia) | C26: =SUM(C13:C24) | D26: =SUM(D13:D24)
A27: Solo los rubros marcados Si en la columna G cuentan como C_presup; deben cubrir lo mismo que los sprints con programacion.

Sheet costo_real_sprint
A1: Costo real por sprint (proyecto de practicas)
A2: Horas totales de todo el proyecto (alcance completo) y costos reales de IA. Las horas de las cuatro actividades son opcionales.
A4: sprint | B4: fecha inicio | C4: fecha fin | D4: horas totales | E4: horas codificacion | F4: horas pruebas | G4: horas depuracion | H4: horas correcciones | I4: horas 4 actividades | J4: revision | K4: licencias (USD) | L4: API (USD) | M4: capacitacion (USD) | N4: integracion (USD) | O4: observaciones | P4: hubo programacion (Si/No)
A5: 1 | B5: aaaa-mm-dd | C5: aaaa-mm-dd | D5: 0,0 | E5: 0,0 | F5: 0,0 | G5: 0,0 | H5: 0,0 | I5: formula | J5: formula | K5: 0,00 | L5: 0,00 | M5: 0,00 | N5: 0,00 | O5: texto | P5: Si
A6: 1 | B6: 46034 | C6: 46045 | D6: 460 | E6: 250 | F6: 110 | G6: 45 | H6: 25 | I6: =IF(COUNT(E6:H6)=0,"",SUM(E6:H6)) | J6: =IF(OR(D6="",I6=""),"",IF(I6>D6,"revisar","ok")) | K6: 160 | L6: 55 | M6: 320 | N6: 400 | O6: Sprint 1: Onboarding y entidades base | P6: Si
A7: 2 | B7: 46048 | C7: 46059 | D7: 440 | E7: 240 | F7: 115 | G7: 40 | H7: 20 | I7: =IF(COUNT(E7:H7)=0,"",SUM(E7:H7)) | J7: =IF(OR(D7="",I7=""),"",IF(I7>D7,"revisar","ok")) | K7: 160 | L7: 65 | M7: 60 | N7: 100 | O7: Sprint 2: APIs de asistencia y logica | P7: Si
A8: 3 | B8: 46062 | C8: 46073 | D8: 420 | E8: 230 | F8: 105 | G8: 35 | H8: 20 | I8: =IF(COUNT(E8:H8)=0,"",SUM(E8:H8)) | J8: =IF(OR(D8="",I8=""),"",IF(I8>D8,"revisar","ok")) | K8: 160 | L8: 60 | M8: 0 | N8: 50 | O8: Sprint 3: Vistas y reportes UGEL | P8: Si
A9: 4 | B9: 46076 | C9: 46087 | D9: 380 | E9: 190 | F9: 110 | G9: 30 | H9: 20 | I9: =IF(COUNT(E9:H9)=0,"",SUM(E9:H9)) | J9: =IF(OR(D9="",I9=""),"",IF(I9>D9,"revisar","ok")) | K9: 160 | L9: 45 | M9: 0 | N9: 0 | O9: Sprint 4: QA integral y entrega | P9: Si
A10: 5 | I10: =IF(COUNT(E10:H10)=0,"",SUM(E10:H10)) | J10: =IF(OR(D10="",I10=""),"",IF(I10>D10,"revisar","ok"))
A11: 6 | I11: =IF(COUNT(E11:H11)=0,"",SUM(E11:H11)) | J11: =IF(OR(D11="",I11=""),"",IF(I11>D11,"revisar","ok"))
A12: 7 | I12: =IF(COUNT(E12:H12)=0,"",SUM(E12:H12)) | J12: =IF(OR(D12="",I12=""),"",IF(I12>D12,"revisar","ok"))
A13: 8 | I13: =IF(COUNT(E13:H13)=0,"",SUM(E13:H13)) | J13: =IF(OR(D13="",I13=""),"",IF(I13>D13,"revisar","ok"))
A14: 9 | I14: =IF(COUNT(E14:H14)=0,"",SUM(E14:H14)) | J14: =IF(OR(D14="",I14=""),"",IF(I14>D14,"revisar","ok"))
A15: 10 | I15: =IF(COUNT(E15:H15)=0,"",SUM(E15:H15)) | J15: =IF(OR(D15="",I15=""),"",IF(I15>D15,"revisar","ok"))
A16: 11 | I16: =IF(COUNT(E16:H16)=0,"",SUM(E16:H16)) | J16: =IF(OR(D16="",I16=""),"",IF(I16>D16,"revisar","ok"))
A17: 12 | I17: =IF(COUNT(E17:H17)=0,"",SUM(E17:H17)) | J17: =IF(OR(D17="",I17=""),"",IF(I17>D17,"revisar","ok"))
A18: TOTAL en alcance (sprints con programacion) | D18: =SUMIF($P$6:$P$17,"Si",D6:D17) | E18: =SUMIF($P$6:$P$17,"Si",E6:E17) | F18: =SUMIF($P$6:$P$17,"Si",F6:F17) | G18: =SUMIF($P$6:$P$17,"Si",G6:G17) | H18: =SUMIF($P$6:$P$17,"Si",H6:H17) | I18: =SUMIF($P$6:$P$17,"Si",I6:I17) | K18: =SUMIF($P$6:$P$17,"Si",K6:K17) | L18: =SUMIF($P$6:$P$17,"Si",L6:L17) | M18: =SUMIF($P$6:$P$17,"Si",M6:M17) | N18: =SUMIF($P$6:$P$17,"Si",N6:N17)
A19: TOTAL de todos los sprints (referencia) | D19: =SUM(D6:D17) | E19: =SUM(E6:E17) | F19: =SUM(F6:F17) | G19: =SUM(G6:G17) | H19: =SUM(H6:H17) | I19: =SUM(I6:I17) | K19: =SUM(K6:K17) | L19: =SUM(L6:L17) | M19: =SUM(M6:M17) | N19: =SUM(N6:N17)
A20: C_real (F33) usa solo la fila en alcance. Marca No en los sprints sin programacion y explica en observaciones.

Sheet constantes
A1: Constantes COCOMO II.2000 Post-Architecture (fijas)
A2: Fuente: manual COCOMO II.2000 (CII_modelman2000). No editar salvo que se recalibre con datos propios.
A4: constante | B4: valor | C4: uso / nota
A5: A | B5: 2.94 | C5: Constante multiplicativa del esfuerzo (F3)
A6: B | B6: 0.91 | C6: Exponente base (F2, F4)
A7: C | B7: 3.67 | C7: Constante del plazo (F5)
A8: D | B8: 0.28 | C8: Constante del exponente de plazo (F4)
A9: horas_por_PM | B9: 152 | C9: Horas por persona-mes (F6, F8)
A10: PREC nominal | B10: 3.72 | C10: Factor de escala, nivel nominal
A11: FLEX nominal | B11: 3.04 | C11: Factor de escala, nivel nominal
A12: RESL nominal | B12: 4.24 | C12: Factor de escala, nivel nominal
A13: TEAM nominal | B13: 3.29 | C13: Factor de escala, nivel nominal
A14: PMAT nominal | B14: 4.68 | C14: Factor de escala, nivel nominal
A15: EM nominal | B15: 1 | C15: Multiplicador de esfuerzo nominal
A16: SCED% nominal | B16: 100 | C16: Compresion de plazo nominal (porcentaje)

Sheet verificacion
A1: Verificacion de formulas F1 a F8 (se recalcula sola)
A2: Bloque 1 prueba las constantes con 100 KSLOC nominal. Bloque 2 calcula el proyecto de la hoja proyecto.
A4: Bloque 1: prueba con constantes nominales | B4: valor | C4: esperado | D4: nota
A5: Tamano de prueba (KSLOC) | B5: 100
A6: Suma SF (F1) | B6: =constantes!$B$10+constantes!$B$11+constantes!$B$12+constantes!$B$13+constantes!$B$14 | C6: 18.97
A7: E (F2) | B7: =constantes!$B$6+0.01*B6 | C7: 1.0997
A8: PM (F3) | B8: =constantes!$B$5*B5^B7*constantes!$B$15 | C8: 465.3 | D8: Esperados de la verificacion numerica propia (no son datos de un estudio)
A9: phi (F4) | B9: =constantes!$B$8+0.2*(B7-constantes!$B$6) | C9: 0.318
A10: TDEV (meses) (F5) | B10: =constantes!$B$7*B8^B9*constantes!$B$16/100 | C10: 25.9
A11: Horas totales (PM x 152) | B11: =B8*constantes!$B$9 | C11: 70726
A12: Resultado de la prueba | B12: =IF(AND(ABS(B6-C6)<0.005,ABS(B7-C7)<0.0005,ABS(B8-C8)<0.1,ABS(B9-C9)<0.001,ABS(B10-C10)<0.1,ABS(B11-C11)<20),"ok","revisar")
A15: Bloque 2: proyecto de la hoja proyecto | B15: valor | C15: unidad | D15: formula
A16: Suma SF | B16: =IF(proyecto!$C$7="","",proyecto!$C$8+proyecto!$C$9+proyecto!$C$10+proyecto!$C$11+proyecto!$C$12) | C16: adimensional | D16: F1
A17: E | B17: =IF(B16="","",constantes!$B$6+0.01*B16) | C17: adimensional | D17: F2
A18: PM sin SCED (PM_NS) | B18: =IF(B16="","",constantes!$B$5*proyecto!$C$7^B17*PRODUCT(proyecto!$C$13:$C$28)) | C18: persona-mes | D18: F3 sin multiplicador SCED
A19: PM (con multiplicador SCED) | B19: =IF(B16="","",B18*proyecto!$C$29) | C19: persona-mes | D19: F3
A20: phi | B20: =IF(B16="","",constantes!$B$8+0.2*(B17-constantes!$B$6)) | C20: adimensional | D20: F4
A21: TDEV | B21: =IF(B16="","",constantes!$B$7*B18^B20*proyecto!$C$30/100) | C21: meses | D21: F5
A22: Tarifa por hora t_h | B22: =IF(proyecto!$C$31="","",proyecto!$C$31/constantes!$B$9) | C22: USD / hora | D22: F6
A23: Costo tradicional C_trad | B23: =IF(OR(B16="",proyecto!$C$31=""),"",B19*proyecto!$C$31) | C23: USD | D23: F7
A24: Horas reducibles H_trad | B24: =IF(OR(B16="",proyecto!$C$32=""),"",proyecto!$C$32*B19*constantes!$B$9) | C24: horas | D24: F8
A25: Duracion T usada | B25: =IF(proyecto!$C$33<>"",proyecto!$C$33,IF(B21="","",B21)) | C25: meses | D25: T o TDEV por defecto

Sheet rangos
A1: Rangos que valida M0 antes de calcular
A2: Si un valor sale del rango, M0 se detiene y indica el campo. Los rangos de f vienen del manual; los de los agentes dependen de la literatura.
A4: parametro | B4: minimo permitido | C4: maximo permitido | D4: tipo de control | E4: nota
A5: r | B5: 0 | C5: 1 | D5: error | E5: Fraccion
A6: f | B6: 0.55 | C6: 0.61 | D6: advertencia | E6: Rango sugerido del manual (E = 1,0997; 8 a 128 KSLOC). Fuera del rango exige declarar el supuesto
A7: Size (KSLOC) | B7: 0 | D7: error | E7: Mayor que 0; logicas
A8: c_pm | B8: 0 | D8: error | E8: Mayor que 0
A9: rho_rev, rho_retr | B9: 0 | D9: error | E9: Mayor o igual que 0
A10: delta | B10: 0 | D10: error | E10: Mayor o igual que 0
A11: c_api_h, h_def, p_lic, h_cap, h_int | B11: 0 | D11: error | E11: Mayor o igual que 0
A12: minimo <= esperado <= maximo | D12: error | E12: Aplica a todos los parametros de agentes
A13: Error relativo exito (F34) | C13: 0.25 | D13: criterio | E13: PRED(25); Conte et al. (1986) por verificar en la fuente original
